ontobot_change_agent/__init__.py
ontobot_change_agent/__main__.py
ontobot_change_agent/api.py
ontobot_change_agent/cli.py
ontobot_change_agent/constants.py
ontobot_change_agent/version.py
ontobot_change_agent-0.5.1.dist-info/LICENSE
ontobot_change_agent-0.5.1.dist-info/METADATA
ontobot_change_agent-0.5.1.dist-info/WHEEL
ontobot_change_agent-0.5.1.dist-info/entry_points.txt
ontobot_change_agent-0.5.1.dist-info/RECORD
