Metadata-Version: 2.1
Name: ontobot-change-agent
Version: 0.5.1
Summary: Update ontologies using change language.
License: MIT
Author: Harshad Hegde
Author-email: hhegde@lbl.gov
Requires-Python: >=3.9,<4.0.0
Classifier: License :: OSI Approved :: MIT License
Classifier: Programming Language :: Python :: 3
Classifier: Programming Language :: Python :: 3.9
Classifier: Programming Language :: Python :: 3.10
Classifier: Programming Language :: Python :: 3.11
Classifier: Programming Language :: Python :: 3.12
Provides-Extra: docs
Provides-Extra: llm
Requires-Dist: PyGithub (>=2.3.0,<3.0.0)
Requires-Dist: llm-change-agent[llm] (>=0.0.9,<0.0.10) ; extra == "llm"
Requires-Dist: oaklib (>=0.5.0)
Requires-Dist: setuptools (>=70.1.1)
